pycmake/__init__.py
pycmake/cmake.py
pycmake/cmake_command.py
pycmake/cmake_variable.py
pycmake/command_builder.py
pycmake/input_args.py
pycmake/pycmake_variable.py
pycmake/utils.py
pycmake-0.1.1.dist-info/METADATA
pycmake-0.1.1.dist-info/WHEEL
pycmake-0.1.1.dist-info/licenses/LICENSE
pycmake-0.1.1.dist-info/RECORD
