Metadata-Version: 2.1
Name: pycmake
Version: 0.1.1
Summary: Python bindings for CMake.
Author-email: "Francis J. Sun" <francisjsun@outlook.com>
License-File: LICENSE
